{
  "date": "2025-12-04",
  "snapshots": [
    {
      "timestamp": "2025-12-04T00:00:05.868803+00:00",
      "call_count": 8,
      "calls": [
        {
          "Master_Incident_Number": "120325-00469",
          "Online_Description": "HIT & RUN",
          "Address": "COUNTRYSIDE BLVD / SR 580",
          "Response_Date": "2025-12-03T17:30:32"
        },
        {
          "Master_Incident_Number": "120325-00494",
          "Online_Description": "PARK WALK AND TALK",
          "Address": "2100 BLOCK GULF TO BAY BLVD",
          "Response_Date": "2025-12-03T18:27:30"
        },
        {
          "Master_Incident_Number": "120325-00495",
          "Online_Description": "DIRECTED PATROL",
          "Address": "COURT ST / S MADISON AVE",
          "Response_Date": "2025-12-03T18:28:22"
        },
        {
          "Master_Incident_Number": "120325-00497",
          "Online_Description": "911 HANG-UP",
          "Address": "600 BLOCK S GULFVIEW BLVD",
          "Response_Date": "2025-12-03T18:29:33"
        },
        {
          "Master_Incident_Number": "120325-00498",
          "Online_Description": "SUSPICIOUS VEHICLE",
          "Address": "N MYRTLE AVE / MARGO AVE",
          "Response_Date": "2025-12-03T18:33:18"
        },
        {
          "Master_Incident_Number": "120325-00502",
          "Online_Description": "MISSING PERSON",
          "Address": "1700 BLOCK W MANOR AVE",
          "Response_Date": "2025-12-03T18:35:18"
        },
        {
          "Master_Incident_Number": "120325-00500",
          "Online_Description": "TRAFFIC STOP",
          "Address": "MEMORIAL CSWY / ISLAND WAY",
          "Response_Date": "2025-12-03T18:36:06"
        },
        {
          "Master_Incident_Number": "120325-00501",
          "Online_Description": "TRAFFIC STOP",
          "Address": "S MARTIN LUTHER KING JR AVE / TURNER ST",
          "Response_Date": "2025-12-03T18:36:27"
        }
      ]
    },
    {
      "timestamp": "2025-12-04T02:04:40.400910+00:00",
      "call_count": 6,
      "calls": [
        {
          "Master_Incident_Number": "120325-00559",
          "Online_Description": "NOISE COMPLAINT",
          "Address": "100 BLOCK DEVON DR",
          "Response_Date": "2025-12-03T20:15:06"
        },
        {
          "Master_Incident_Number": "120325-00560",
          "Online_Description": "TRAFFIC CRASH",
          "Address": "MEADOW WOOD DR / COUNTRYSIDE BLVD",
          "Response_Date": "2025-12-03T20:17:42"
        },
        {
          "Master_Incident_Number": "120325-00565",
          "Online_Description": "TRAFFIC STOP",
          "Address": "DREW ST / N BELCHER RD",
          "Response_Date": "2025-12-03T20:32:34"
        },
        {
          "Master_Incident_Number": "120325-00566",
          "Online_Description": "TRAFFIC STOP",
          "Address": "1200 BLOCK S MISSOURI AVE",
          "Response_Date": "2025-12-03T20:36:38"
        },
        {
          "Master_Incident_Number": "120325-00567",
          "Online_Description": "UNKNOWN PROBLEM",
          "Address": "900 BLOCK SEMINOLE ST",
          "Response_Date": "2025-12-03T20:37:54"
        },
        {
          "Master_Incident_Number": "120325-00568",
          "Online_Description": "TRAFFIC STOP",
          "Address": "DREW ST / N BELCHER RD",
          "Response_Date": "2025-12-03T20:40:56"
        }
      ]
    },
    {
      "timestamp": "2025-12-04T03:34:57.207123+00:00",
      "call_count": 9,
      "calls": [
        {
          "Master_Incident_Number": "120325-00565",
          "Online_Description": "TRAFFIC STOP",
          "Address": "DREW ST / N BELCHER RD",
          "Response_Date": "2025-12-03T20:32:34"
        },
        {
          "Master_Incident_Number": "120325-00571",
          "Online_Description": "THEFT",
          "Address": "400 BLOCK S AURORA AVE",
          "Response_Date": "2025-12-03T20:49:00"
        },
        {
          "Master_Incident_Number": "120325-00594",
          "Online_Description": "FRAUD",
          "Address": "2400 BLOCK NORTHSIDE DR",
          "Response_Date": "2025-12-03T21:26:18"
        },
        {
          "Master_Incident_Number": "120325-00603",
          "Online_Description": "TRESPASS",
          "Address": "1600 BLOCK N HIGHLAND AVE",
          "Response_Date": "2025-12-03T21:45:04"
        },
        {
          "Master_Incident_Number": "120325-00607",
          "Online_Description": "CRIMINAL MISCHIEF",
          "Address": "1400 BLOCK S MARTIN LUTHER KING JR AVE",
          "Response_Date": "2025-12-03T21:50:05"
        },
        {
          "Master_Incident_Number": "120325-00609",
          "Online_Description": "911 HANG-UP",
          "Address": "900 BLOCK SEMINOLE ST",
          "Response_Date": "2025-12-03T22:02:53"
        },
        {
          "Master_Incident_Number": "120325-00611",
          "Online_Description": "WELFARE CHECK",
          "Address": "2800 BLOCK CHANCERY LN",
          "Response_Date": "2025-12-03T22:08:41"
        },
        {
          "Master_Incident_Number": "120325-00612",
          "Online_Description": "TRAFFIC STOP",
          "Address": "GULF TO BAY BLVD / US HIGHWAY 19 N",
          "Response_Date": "2025-12-03T22:10:55"
        },
        {
          "Master_Incident_Number": "120325-00613",
          "Online_Description": "TRAFFIC STOP",
          "Address": "PARK ST / S EAST AVE",
          "Response_Date": "2025-12-03T22:11:10"
        }
      ]
    },
    {
      "timestamp": "2025-12-04T04:05:21.953709+00:00",
      "call_count": 5,
      "calls": [
        {
          "Master_Incident_Number": "120325-00565",
          "Online_Description": "TRAFFIC STOP",
          "Address": "DREW ST / N BELCHER RD",
          "Response_Date": "2025-12-03T20:32:34"
        },
        {
          "Master_Incident_Number": "120325-00571",
          "Online_Description": "BURGLARY",
          "Address": "400 BLOCK S AURORA AVE",
          "Response_Date": "2025-12-03T20:49:00"
        },
        {
          "Master_Incident_Number": "120325-00594",
          "Online_Description": "FRAUD",
          "Address": "2400 BLOCK NORTHSIDE DR",
          "Response_Date": "2025-12-03T21:26:18"
        },
        {
          "Master_Incident_Number": "120325-00621",
          "Online_Description": "DIRECTED PATROL",
          "Address": "2500 BLOCK ENTERPRISE RD E",
          "Response_Date": "2025-12-03T22:37:54"
        },
        {
          "Master_Incident_Number": "120325-00622",
          "Online_Description": "DIRECTED PATROL",
          "Address": "SANF KEY BRIDGE",
          "Response_Date": "2025-12-03T22:44:50"
        }
      ]
    },
    {
      "timestamp": "2025-12-04T04:39:59.669733+00:00",
      "call_count": 5,
      "calls": [
        {
          "Master_Incident_Number": "120325-00565",
          "Online_Description": "TRAFFIC STOP",
          "Address": "DREW ST / N BELCHER RD",
          "Response_Date": "2025-12-03T20:32:34"
        },
        {
          "Master_Incident_Number": "120325-00571",
          "Online_Description": "BURGLARY",
          "Address": "400 BLOCK S AURORA AVE",
          "Response_Date": "2025-12-03T20:49:00"
        },
        {
          "Master_Incident_Number": "120325-00622",
          "Online_Description": "DIRECTED PATROL",
          "Address": "600 BLOCK GULF BLVD",
          "Response_Date": "2025-12-03T22:44:50"
        },
        {
          "Master_Incident_Number": "120325-00633",
          "Online_Description": "BURGLARY",
          "Address": "1100 BLOCK GROVE ST",
          "Response_Date": "2025-12-03T23:08:55"
        },
        {
          "Master_Incident_Number": "120325-00635",
          "Online_Description": "TRESPASS",
          "Address": "300 BLOCK PINELLAS ST",
          "Response_Date": "2025-12-03T23:17:30"
        }
      ]
    }
  ]
}